panda3d_rest/__init__.py
panda3d_rest/http.py
panda3d_rest/request.py
panda3d_rest-1.0.3.dist-info/LICENSE
panda3d_rest-1.0.3.dist-info/METADATA
panda3d_rest-1.0.3.dist-info/WHEEL
panda3d_rest-1.0.3.dist-info/top_level.txt
panda3d_rest-1.0.3.dist-info/RECORD
